LICENSE
README.md
setup.py
CVE_2020_3187.egg-info/PKG-INFO
CVE_2020_3187.egg-info/SOURCES.txt
CVE_2020_3187.egg-info/dependency_links.txt
CVE_2020_3187.egg-info/entry_points.txt
CVE_2020_3187.egg-info/requires.txt
CVE_2020_3187.egg-info/top_level.txt
cve20203187/__init__.py
cve20203187/main.py
cve20203187/includes/__init__.py
cve20203187/includes/bot.py
cve20203187/includes/filereader.py
cve20203187/includes/scan.py
cve20203187/includes/writefile.py
cve20203187/utils/__init__.py
cve20203187/utils/configure.py
cve20203187/utils/const.py
cve20203187/utils/helpers.py
cve20203187/utils/status.py